encoder.vhd
LIBRARY ieee;
USE ieee.std_logic_1164.ALL;
USE ieee.numeric_std.ALL;

ENTITY encoder IS
    PORT (
        cipher : IN STD_LOGIC_VECTOR(15 DOWNTO 0);
        message : IN STD_LOGIC_VECTOR(7 DOWNTO 0);
        encrypted_text : OUT STD_LOGIC_VECTOR(7 DOWNTO 0) -- this is the encrypted message
    );
END encoder;

ARCHITECTURE encoder_arch OF encoder IS
BEGIN

    encrypted_text <= cipher(7 DOWNTO 0) XOR message;

END encoder_arch;

LFSR.vhd
LIBRARY ieee;
USE ieee.std_logic_1164.ALL;
USE ieee.numeric_std.ALL;

ENTITY LFSR IS
    PORT (
        reset_n : IN STD_LOGIC;
        clk : IN STD_LOGIC;
        cipher_out : OUT STD_LOGIC_VECTOR(15 DOWNTO 0)
    );

END LFSR;

ARCHITECTURE LFSR_ARCH OF LFSR IS
    SIGNAL temp : STD_LOGIC;
    SIGNAL to_out : STD_LOGIC_VECTOR(15 DOWNTO 0);

BEGIN

    temp <= to_out(10) XOR (to_out(12) XOR (to_out(14) XOR to_out(15)));
    cipher <= to_out;
    PROCESS (clk)
    BEGIN
        IF rising_edge(clk) THEN
            IF NOT reset_n THEN
                to_out <= x"A5A5";
            ELSE
                to_out <= temp & to_out(15 : 1);
            END IF;
        END IF;
    END PROCESS;
END

END LFSR_ARCH;

testbench.vhd
LIBRARY ieee;
USE ieee.std_logic_1164.ALL;

ENTITY testbench IS
END testbench;

ARCHITECTURE test OF testbench IS
    SIGNAL clk : STD_LOGIC := '0';
    SIGNAL reset_n : STD_LOGIC := '0';
    SIGNAL cipher_out : STD_LOGIC_VECTOR(15 DOWNTO 0);
    SIGNAL message : STD_LOGIC_VECTOR(7 DOWNTO 0);
    SIGNAL encrypted_text : STD_LOGIC_VECTOR(7 DOWNTO 0);

BEGIN
    -- Instantiate LFSR
    LFSR_inst : ENTITY work.LFSR
        PORT MAP(
            clk => clk,
            reset_n => reset_n,
            cipher_out => cipher_out
        );

    -- Instantiate encoder
    encoder_inst : ENTITY work.encoder
        PORT MAP(
            cipher => cipher_out,
            message => message,
            encrypted_text => encrypted_text
        );

    -- Clock generation
    clk <= NOT clk AFTER 5 ns;

    -- Test stimulus
    PROCESS
    BEGIN
        -- Hold in reset for initial cycles
        -- Expected: cipher_out held at x"A5A5" (init value); cipher_text = x"A5" XOR x"00" = x"A5"
        reset_n <= '0';
        message <= x"00";
        WAIT FOR 20 ns;

        -- Release reset
        -- Expected: LFSR begins shifting and produces new keystream each clock; cipher_text evolves
        reset_n <= '1';
        message <= x"AA";
        WAIT FOR 20 ns;

        -- Change message
        -- Expected: LFSR continues shifting; cipher_text = cipher_out(7:0) XOR x"55"
        message <= x"55";
        WAIT FOR 20 ns;

        -- Change message again
        -- Expected: LFSR continues shifting; cipher_text = cipher_out(7:0) XOR x"FF"
        message <= x"FF";
        WAIT FOR 20 ns;

        -- Change message
        -- Expected: LFSR continues shifting; cipher_text = cipher_out(7:0) XOR x"AA"
        message <= x"AA";
        WAIT FOR 20 ns;

        -- End test stimulus and idle
        WAIT;
    END PROCESS;

END test;

output.vcd
$date
  Wed Apr 08 21:25:29 2026
$end
$version
  GHDL v0
$end
$timescale
  1 fs
$end
$scope module standard $end
$upscope $end
$scope module std_logic_1164 $end
$upscope $end
$scope module numeric_std $end
$upscope $end
$scope module testbench $end
$var reg 1 ! clk $end
$var reg 1 " reset_n $end
$var reg 16 # cipher_out[15:0] $end
$var reg 8 $ message[7:0] $end
$var reg 8 % encrypted_text[7:0] $end
$scope module lfsr_inst $end
$var reg 1 & reset_n $end
$var reg 1 ' clk $end
$var reg 16 ( cipher_out[15:0] $end
$var reg 1 ) temp $end
$var reg 16 * to_out[15:0] $end
$upscope $end
$scope module encoder_inst $end
$var reg 16 + cipher[15:0] $end
$var reg 8 , message[7:0] $end
$var reg 8 - encrypted_text[7:0] $end
$upscope $end
$upscope $end
$enddefinitions $end
#0
0!
0"
b1010010110100101 #
b00000000 $
b10100101 %
0&
0'
b1010010110100101 (
0)
b1010010110100101 *
b1010010110100101 +
b00000000 ,
b10100101 -
#5000000
1!
1'
#10000000
0!
0'
#15000000
1!
1'
#20000000
0!
1"
b10101010 $
b00001111 %
1&
0'
b10101010 ,
b00001111 -
#25000000
1!
b0101001011010010 #
b01111000 %
1'
b0101001011010010 (
b0101001011010010 *
b0101001011010010 +
b01111000 -
#30000000
0!
0'
#35000000
1!
b0010100101101001 #
b11000011 %
1'
b0010100101101001 (
b0010100101101001 *
b0010100101101001 +
b11000011 -
#40000000
0!
b01010101 $
b00111100 %
0'
b01010101 ,
b00111100 -
#45000000
1!
b0001010010110100 #
b11100001 %
1'
b0001010010110100 (
b0001010010110100 *
b0001010010110100 +
b11100001 -
#50000000
0!
0'
#55000000
1!
b0000101001011010 #
b00001111 %
1'
b0000101001011010 (
b0000101001011010 *
b0000101001011010 +
b00001111 -
#60000000
0!
b11111111 $
b10100101 %
0'
b11111111 ,
b10100101 -
#65000000
1!
b0000010100101101 #
b11010010 %
1'
b0000010100101101 (
1)
b0000010100101101 *
b0000010100101101 +
b11010010 -
#70000000
0!
0'
#75000000
1!
b1000001010010110 #
b01101001 %
1'
b1000001010010110 (
b1000001010010110 *
b1000001010010110 +
b01101001 -
#80000000
0!
b10101010 $
b00111100 %
0'
b10101010 ,
b00111100 -
#85000000
1!
b1100000101001011 #
b11100001 %
1'
b1100000101001011 (
0)
b1100000101001011 *
b1100000101001011 +
b11100001 -
#90000000
0!
0'
#95000000
1!
b0110000010100101 #
b00001111 %
1'
b0110000010100101 (
1)
b0110000010100101 *
b0110000010100101 +
b00001111 -
#100000000
0!
0'
#105000000
1!
b1011000001010010 #
b11111000 %
1'
b1011000001010010 (
0)
b1011000001010010 *
b1011000001010010 +
b11111000 -
#110000000
0!
0'
#115000000
1!
b0101100000101001 #
b10000011 %
1'
b0101100000101001 (
b0101100000101001 *
b0101100000101001 +
b10000011 -
