hardware/codec.vhd
LIBRARY ieee;
USE ieee.std_logic_1164.ALL;
USE ieee.numeric_std.ALL;

ENTITY codec IS
    PORT (
        cipher : IN STD_LOGIC_VECTOR(15 DOWNTO 0);
        message : IN STD_LOGIC_VECTOR(7 DOWNTO 0);
        out_text : OUT STD_LOGIC_VECTOR(7 DOWNTO 0) -- this is the encrypted/deciphered message
    );
END codec;

ARCHITECTURE codec_arch OF codec IS
BEGIN

    out_text <= cipher(7 DOWNTO 0) XOR message;

END codec_arch;

hardware/LFSR.vhd
LIBRARY ieee;
USE ieee.std_logic_1164.ALL;
USE ieee.numeric_std.ALL;

ENTITY LFSR IS
    PORT (
        reset_n : IN STD_LOGIC;
        clk : IN STD_LOGIC;
        enable : IN STD_LOGIC;
        cipher_out : OUT STD_LOGIC_VECTOR(15 DOWNTO 0) --This is the cipher for the encoder
    );

END LFSR;

ARCHITECTURE LFSR_ARCH OF LFSR IS
    SIGNAL temp : STD_LOGIC;
    SIGNAL to_out : STD_LOGIC_VECTOR(15 DOWNTO 0) := x"A5A5";

BEGIN
    temp <= to_out(10) XOR (to_out(12) XOR (to_out(14) XOR to_out(15)));
    cipher_out <= to_out;

    PROCESS (clk)

    BEGIN
        IF rising_edge(clk) THEN
            IF reset_n = '0' THEN
                to_out <= x"A5A5";
            ELSIF enable = '1' THEN
                to_out <= temp & to_out(15 DOWNTO 1);
            ELSE
                to_out <= to_out;
            END IF;
        END IF;
    END PROCESS;

END LFSR_ARCH;

hardware/codec_top.vhd
LIBRARY ieee;
USE ieee.std_logic_1164.ALL;
USE ieee.numeric_std.ALL;

ENTITY codec_top IS
    PORT (
        tmessage : IN STD_LOGIC_VECTOR(7 DOWNTO 0);
        treset_n : IN STD_LOGIC;
        tclk : IN STD_LOGIC;
        start_msg : IN STD_LOGIC;
        counter_value : IN UNSIGNED(15 DOWNTO 0);
        tenable : IN STD_LOGIC;
        encrypted : OUT STD_LOGIC_VECTOR(7 DOWNTO 0)
    );
END codec_top;

ARCHITECTURE codec_top_arch OF codec_top IS

    SIGNAL cipher_wire : STD_LOGIC_VECTOR(15 DOWNTO 0);
    SIGNAL encrypted_message_wire : STD_LOGIC_VECTOR(7 DOWNTO 0);
    SIGNAL lfsr_enable : STD_LOGIC := '0';
    SIGNAL prerun_active : STD_LOGIC := '0';
    SIGNAL prerun_count : UNSIGNED(15 DOWNTO 0) := (OTHERS => '0');

BEGIN
    encrypted <= encrypted_message_wire;

    PROCESS (tclk)
    BEGIN
        IF rising_edge(tclk) THEN
            IF treset_n = '0' THEN
                prerun_active <= '0';
                prerun_count <= (OTHERS => '0');
                lfsr_enable <= '0';
            ELSIF start_msg = '1' THEN
                prerun_count <= counter_value;
                IF counter_value = 0 THEN
                    prerun_active <= '0';
                    lfsr_enable <= tenable;
                ELSE
                    prerun_active <= '1';
                    lfsr_enable <= '0';
                END IF;
            ELSIF prerun_active = '1' THEN
                lfsr_enable <= '1';
                IF prerun_count = 1 THEN
                    prerun_count <= (OTHERS => '0');
                    prerun_active <= '0';
                ELSE
                    prerun_count <= prerun_count - 1;
                END IF;
            ELSE
                lfsr_enable <= tenable;
            END IF;
        END IF;
    END PROCESS;

    u_LFSR : ENTITY work.LFSR(LFSR_ARCH)
        PORT MAP(
            clk => tclk,
            reset_n => treset_n,
            enable => lfsr_enable,
            cipher_out => cipher_wire
        );
    u_codec : ENTITY work.codec(codec_arch)
        PORT MAP(
            cipher => cipher_wire,
            message => tmessage,
            out_text => encrypted_message_wire
        );
END codec_top_arch;

hardware/enc_dec_top.vhd
LIBRARY ieee;
USE ieee.std_logic_1164.ALL;
USE ieee.numeric_std.ALL;

ENTITY enc_dec_top IS
    PORT (
        in_message : IN STD_LOGIC_VECTOR(7 DOWNTO 0);
        reset : IN STD_LOGIC;
        clock : IN STD_LOGIC;
        start_msg : IN STD_LOGIC;
        counter_value : IN UNSIGNED(15 DOWNTO 0);
        enable : IN STD_LOGIC;
        out_encrypted : OUT STD_LOGIC_VECTOR(7 DOWNTO 0);
        out_deciphered : OUT STD_LOGIC_VECTOR(7 DOWNTO 0)
    );
END enc_dec_top;

ARCHITECTURE enc_dec_top_arch OF enc_dec_top IS
    --encoder to decoder
    SIGNAL enc_to_dec : STD_LOGIC_VECTOR(7 DOWNTO 0);

    --
BEGIN
    out_encrypted <= enc_to_dec;
    u_encoder : ENTITY work.codec_top(codec_top_arch)
        PORT MAP(
            tmessage => in_message,
            treset_n => reset,
            tclk => clock,
            start_msg => start_msg,
            counter_value => counter_value,
            tenable => enable,
            encrypted => enc_to_dec
        );

    u_decoder : ENTITY work.codec_top(codec_top_arch)
        PORT MAP(
            tmessage => enc_to_dec,
            treset_n => reset,
            tclk => clock,
            start_msg => start_msg,
            counter_value => counter_value,
            tenable => enable,
            encrypted => out_deciphered
        );
END enc_dec_top_arch;

hardware/testbench.vhd
LIBRARY ieee;
USE ieee.std_logic_1164.ALL;
USE ieee.numeric_std.ALL;

ENTITY testbench IS
END testbench;

ARCHITECTURE test OF testbench IS
    SIGNAL clk : STD_LOGIC := '0';
    SIGNAL reset_n : STD_LOGIC := '0';
    SIGNAL start_msg : STD_LOGIC := '0';
    SIGNAL counter_value : UNSIGNED(15 DOWNTO 0) := (OTHERS => '0');
    SIGNAL enable : STD_LOGIC := '0';
    SIGNAL cipher_out : STD_LOGIC_VECTOR(15 DOWNTO 0);
    SIGNAL message : STD_LOGIC_VECTOR(7 DOWNTO 0);
    SIGNAL encrypted_text : STD_LOGIC_VECTOR(7 DOWNTO 0);
    SIGNAL deciphered_text : STD_LOGIC_VECTOR(7 DOWNTO 0);

BEGIN
    -- Instantiate LFSR
    codec_inst : ENTITY work.enc_dec_top
        PORT MAP(
            in_message => message,
            reset => reset_n,
            clock => clk,
            start_msg => start_msg,
            counter_value => counter_value,
            enable => enable,
            out_encrypted => encrypted_text,
            out_deciphered => deciphered_text
        );

    -- Clock generation
    clk <= NOT clk AFTER 5 ns;

    -- Test stimulus
    PROCESS
    BEGIN
        -- Hold in reset for initial cycles
        reset_n <= '0';
        start_msg <= '0';
        counter_value <= (OTHERS => '0');
        enable <= '0';
        message <= x"00";
        WAIT FOR 20 ns;

        -- Start a message and pre-run LFSR by 3 cycles before data bytes.
        reset_n <= '1';
        counter_value <= to_unsigned(3, 16);
        start_msg <= '1';
        WAIT FOR 10 ns;
        start_msg <= '0';
        WAIT FOR 40 ns;

        -- Byte-valid pulses after pre-run.
        message <= x"AA";
        enable <= '1';
        WAIT FOR 10 ns;
        enable <= '0';
        WAIT FOR 10 ns;

        -- Next byte: pulse enable for one cycle
        message <= x"55";
        enable <= '1';
        WAIT FOR 10 ns;
        enable <= '0';
        WAIT FOR 10 ns;

        -- Next byte: pulse enable for one cycle
        message <= x"FF";
        enable <= '1';
        WAIT FOR 10 ns;
        enable <= '0';
        WAIT FOR 10 ns;

        -- Next byte: pulse enable for one cycle
        message <= x"AA";
        enable <= '1';
        WAIT FOR 10 ns;
        enable <= '0';
        WAIT FOR 10 ns;

        -- End test stimulus and idle
        WAIT;
    END PROCESS;

END test;

hardware/output.vcd
$date
  Fri Apr 17 21:59:38 2026
$end
$version
  GHDL v0
$end
$timescale
  1 fs
$end
$scope module standard $end
$upscope $end
$scope module std_logic_1164 $end
$upscope $end
$scope module numeric_std $end
$upscope $end
$scope module testbench $end
$var reg 1 ! clk $end
$var reg 1 " reset_n $end
$var reg 1 # start_msg $end
$var reg 16 $ counter_value[15:0] $end
$var reg 1 % enable $end
$var reg 16 & cipher_out[15:0] $end
$var reg 8 ' message[7:0] $end
$var reg 8 ( encrypted_text[7:0] $end
$var reg 8 ) deciphered_text[7:0] $end
$scope module codec_inst $end
$var reg 8 * in_message[7:0] $end
$var reg 1 + reset $end
$var reg 1 , clock $end
$var reg 1 - start_msg $end
$var reg 16 . counter_value[15:0] $end
$var reg 1 / enable $end
$var reg 8 0 out_encrypted[7:0] $end
$var reg 8 1 out_deciphered[7:0] $end
$var reg 8 2 enc_to_dec[7:0] $end
$scope module u_encoder $end
$var reg 8 3 tmessage[7:0] $end
$var reg 1 4 treset_n $end
$var reg 1 5 tclk $end
$var reg 1 6 start_msg $end
$var reg 16 7 counter_value[15:0] $end
$var reg 1 8 tenable $end
$var reg 8 9 encrypted[7:0] $end
$var reg 16 : cipher_wire[15:0] $end
$var reg 8 ; encrypted_message_wire[7:0] $end
$var reg 1 < lfsr_enable $end
$var reg 1 = prerun_active $end
$var reg 16 > prerun_count[15:0] $end
$scope module u_lfsr $end
$var reg 1 ? reset_n $end
$var reg 1 @ clk $end
$var reg 1 A enable $end
$var reg 16 B cipher_out[15:0] $end
$var reg 1 C temp $end
$var reg 16 D to_out[15:0] $end
$upscope $end
$scope module u_codec $end
$var reg 16 E cipher[15:0] $end
$var reg 8 F message[7:0] $end
$var reg 8 G out_text[7:0] $end
$upscope $end
$upscope $end
$scope module u_decoder $end
$var reg 8 H tmessage[7:0] $end
$var reg 1 I treset_n $end
$var reg 1 J tclk $end
$var reg 1 K start_msg $end
$var reg 16 L counter_value[15:0] $end
$var reg 1 M tenable $end
$var reg 8 N encrypted[7:0] $end
$var reg 16 O cipher_wire[15:0] $end
$var reg 8 P encrypted_message_wire[7:0] $end
$var reg 1 Q lfsr_enable $end
$var reg 1 R prerun_active $end
$var reg 16 S prerun_count[15:0] $end
$scope module u_lfsr $end
$var reg 1 T reset_n $end
$var reg 1 U clk $end
$var reg 1 V enable $end
$var reg 16 W cipher_out[15:0] $end
$var reg 1 X temp $end
$var reg 16 Y to_out[15:0] $end
$upscope $end
$scope module u_codec $end
$var reg 16 Z cipher[15:0] $end
$var reg 8 [ message[7:0] $end
$var reg 8 \ out_text[7:0] $end
$upscope $end
$upscope $end
$upscope $end
$upscope $end
$enddefinitions $end
#0
0!
0"
0#
b0000000000000000 $
0%
bUUUUUUUUUUUUUUUU &
b00000000 '
b10100101 (
b00000000 )
b00000000 *
0+
0,
0-
b0000000000000000 .
0/
b10100101 0
b00000000 1
b10100101 2
b00000000 3
04
05
06
b0000000000000000 7
08
b10100101 9
b1010010110100101 :
b10100101 ;
0<
0=
b0000000000000000 >
0?
0@
0A
b1010010110100101 B
0C
b1010010110100101 D
b1010010110100101 E
b00000000 F
b10100101 G
b10100101 H
0I
0J
0K
b0000000000000000 L
0M
b00000000 N
b1010010110100101 O
b00000000 P
0Q
0R
b0000000000000000 S
0T
0U
0V
b1010010110100101 W
0X
b1010010110100101 Y
b1010010110100101 Z
b10100101 [
b00000000 \
#5000000
1!
1,
15
1@
1J
1U
#10000000
0!
0,
05
0@
0J
0U
#15000000
1!
1,
15
1@
1J
1U
#20000000
0!
1"
1#
b0000000000000011 $
1+
0,
1-
b0000000000000011 .
14
05
16
b0000000000000011 7
1?
0@
1I
0J
1K
b0000000000000011 L
1T
0U
#25000000
1!
1,
15
1=
b0000000000000011 >
1@
1J
1R
b0000000000000011 S
1U
#30000000
0!
0#
0,
0-
05
06
0@
0J
0K
0U
#35000000
1!
1,
15
1<
b0000000000000010 >
1@
1A
1J
1Q
b0000000000000010 S
1U
1V
#40000000
0!
0,
05
0@
0J
0U
#45000000
1!
b11010010 (
b00000000 )
1,
b11010010 0
b00000000 1
b11010010 2
15
b11010010 9
b0101001011010010 :
b11010010 ;
b0000000000000001 >
1@
b0101001011010010 B
b0101001011010010 D
b0101001011010010 E
b11010010 G
b11010010 H
1J
b00000000 N
b0101001011010010 O
b00000000 P
b0000000000000001 S
1U
b0101001011010010 W
b0101001011010010 Y
b0101001011010010 Z
b11010010 [
b00000000 \
#50000000
0!
0,
05
0@
0J
0U
#55000000
1!
b01101001 (
b00000000 )
1,
b01101001 0
b00000000 1
b01101001 2
15
b01101001 9
b0010100101101001 :
b01101001 ;
0=
b0000000000000000 >
1@
b0010100101101001 B
b0010100101101001 D
b0010100101101001 E
b01101001 G
b01101001 H
1J
b00000000 N
b0010100101101001 O
b00000000 P
0R
b0000000000000000 S
1U
b0010100101101001 W
b0010100101101001 Y
b0010100101101001 Z
b01101001 [
b00000000 \
#60000000
0!
0,
05
0@
0J
0U
#65000000
1!
b10110100 (
b00000000 )
1,
b10110100 0
b00000000 1
b10110100 2
15
b10110100 9
b0001010010110100 :
b10110100 ;
0<
1@
0A
b0001010010110100 B
b0001010010110100 D
b0001010010110100 E
b10110100 G
b10110100 H
1J
b00000000 N
b0001010010110100 O
b00000000 P
0Q
1U
0V
b0001010010110100 W
b0001010010110100 Y
b0001010010110100 Z
b10110100 [
b00000000 \
#70000000
0!
1%
b10101010 '
b00011110 (
b10101010 )
b10101010 *
0,
1/
b00011110 0
b10101010 1
b00011110 2
b10101010 3
05
18
b00011110 9
b00011110 ;
0@
b10101010 F
b00011110 G
b00011110 H
0J
1M
b10101010 N
b10101010 P
0U
b00011110 [
b10101010 \
#75000000
1!
1,
15
1<
1@
1A
1J
1Q
1U
1V
#80000000
0!
0%
0,
0/
05
08
0@
0J
0M
0U
#85000000
1!
b11110000 (
b10101010 )
1,
b11110000 0
b10101010 1
b11110000 2
15
b11110000 9
b0000101001011010 :
b11110000 ;
0<
1@
0A
b0000101001011010 B
b0000101001011010 D
b0000101001011010 E
b11110000 G
b11110000 H
1J
b10101010 N
b0000101001011010 O
b10101010 P
0Q
1U
0V
b0000101001011010 W
b0000101001011010 Y
b0000101001011010 Z
b11110000 [
b10101010 \
#90000000
0!
1%
b01010101 '
b00001111 (
b01010101 )
b01010101 *
0,
1/
b00001111 0
b01010101 1
b00001111 2
b01010101 3
05
18
b00001111 9
b00001111 ;
0@
b01010101 F
b00001111 G
b00001111 H
0J
1M
b01010101 N
b01010101 P
0U
b00001111 [
b01010101 \
#95000000
1!
1,
15
1<
1@
1A
1J
1Q
1U
1V
#100000000
0!
0%
0,
0/
05
08
0@
0J
0M
0U
#105000000
1!
b01111000 (
b01010101 )
1,
b01111000 0
b01010101 1
b01111000 2
15
b01111000 9
b0000010100101101 :
b01111000 ;
0<
1@
0A
b0000010100101101 B
1C
b0000010100101101 D
b0000010100101101 E
b01111000 G
b01111000 H
1J
b01010101 N
b0000010100101101 O
b01010101 P
0Q
1U
0V
b0000010100101101 W
1X
b0000010100101101 Y
b0000010100101101 Z
b01111000 [
b01010101 \
#110000000
0!
1%
b11111111 '
b11010010 (
b11111111 )
b11111111 *
0,
1/
b11010010 0
b11111111 1
b11010010 2
b11111111 3
05
18
b11010010 9
b11010010 ;
0@
b11111111 F
b11010010 G
b11010010 H
0J
1M
b11111111 N
b11111111 P
0U
b11010010 [
b11111111 \
#115000000
1!
1,
15
1<
1@
1A
1J
1Q
1U
1V
#120000000
0!
0%
0,
0/
05
08
0@
0J
0M
0U
#125000000
1!
b01101001 (
b11111111 )
1,
b01101001 0
b11111111 1
b01101001 2
15
b01101001 9
b1000001010010110 :
b01101001 ;
0<
1@
0A
b1000001010010110 B
b1000001010010110 D
b1000001010010110 E
b01101001 G
b01101001 H
1J
b11111111 N
b1000001010010110 O
b11111111 P
0Q
1U
0V
b1000001010010110 W
b1000001010010110 Y
b1000001010010110 Z
b01101001 [
b11111111 \
#130000000
0!
1%
b10101010 '
b00111100 (
b10101010 )
b10101010 *
0,
1/
b00111100 0
b10101010 1
b00111100 2
b10101010 3
05
18
b00111100 9
b00111100 ;
0@
b10101010 F
b00111100 G
b00111100 H
0J
1M
b10101010 N
b10101010 P
0U
b00111100 [
b10101010 \
#135000000
1!
1,
15
1<
1@
1A
1J
1Q
1U
1V
#140000000
0!
0%
0,
0/
05
08
0@
0J
0M
0U
#145000000
1!
b11100001 (
b10101010 )
1,
b11100001 0
b10101010 1
b11100001 2
15
b11100001 9
b1100000101001011 :
b11100001 ;
0<
1@
0A
b1100000101001011 B
0C
b1100000101001011 D
b1100000101001011 E
b11100001 G
b11100001 H
1J
b10101010 N
b1100000101001011 O
b10101010 P
0Q
1U
0V
b1100000101001011 W
0X
b1100000101001011 Y
b1100000101001011 Z
b11100001 [
b10101010 \
