hardware/codec.vhd
LIBRARY ieee;
USE ieee.std_logic_1164.ALL;
USE ieee.numeric_std.ALL;

ENTITY codec IS
    PORT (
        cipher : IN STD_LOGIC_VECTOR(15 DOWNTO 0);
        message : IN STD_LOGIC_VECTOR(7 DOWNTO 0);
        out_text : OUT STD_LOGIC_VECTOR(7 DOWNTO 0) -- this is the encrypted/deciphered message
    );
END codec;

ARCHITECTURE codec_arch OF codec IS
BEGIN

    out_text <= cipher(7 DOWNTO 0) XOR message;

END codec_arch;

hardware/LFSR.vhd
LIBRARY ieee;
USE ieee.std_logic_1164.ALL;
USE ieee.numeric_std.ALL;

ENTITY LFSR IS
    PORT (
        reset_n : IN STD_LOGIC;
        clk : IN STD_LOGIC;
        cipher_out : OUT STD_LOGIC_VECTOR(15 DOWNTO 0) --This is the cipher for the encoder
    );

END LFSR;

ARCHITECTURE LFSR_ARCH OF LFSR IS
    SIGNAL temp : STD_LOGIC;
    SIGNAL to_out : STD_LOGIC_VECTOR(15 DOWNTO 0) := x"A5A5";

BEGIN
    temp <= to_out(10) XOR (to_out(12) XOR (to_out(14) XOR to_out(15)));
    cipher_out <= to_out;

    PROCESS (clk)

    BEGIN
        IF rising_edge(clk) THEN
            IF reset_n = '0' THEN
                to_out <= x"A5A5";
            ELSE
                to_out <= temp & to_out(15 DOWNTO 1);
            END IF;
        END IF;
    END PROCESS;

END LFSR_ARCH;

codec_top.vhd
LIBRARY ieee;
USE ieee.std_logic_1164.ALL;
USE ieee.numeric_std.ALL;

ENTITY codec_top IS
    PORT (
        tmessage : IN STD_LOGIC_VECTOR(7 DOWNTO 0);
        treset_n : IN STD_LOGIC;
        tclk : IN STD_LOGIC;
        encrypted : OUT STD_LOGIC_VECTOR(7 DOWNTO 0)
    );
END codec_top;

ARCHITECTURE codec_top_arch OF codec_top IS

    SIGNAL cipher_wire : STD_LOGIC_VECTOR(15 DOWNTO 0);
    SIGNAL encrypted_message_wire : STD_LOGIC_VECTOR(7 DOWNTO 0);

BEGIN
    encrypted <= encrypted_message_wire;

    u_LFSR : ENTITY work.LFSR(LFSR_ARCH)
        PORT MAP(
            clk => tclk,
            reset_n => treset_n,
            cipher_out => cipher_wire
        );
    u_codec : ENTITY work.codec(codec_arch)
        PORT MAP(
            cipher => cipher_wire,
            message => tmessage,
            out_text => encrypted_message_wire
        );
END codec_top_arch;

enc_dec_top.vhd
LIBRARY ieee;
USE ieee.std_logic_1164.ALL;
USE ieee.numeric_std.ALL;

ENTITY enc_dec_top IS
    PORT (
        in_message : IN STD_LOGIC_VECTOR(7 DOWNTO 0);
        reset : IN STD_LOGIC;
        clock : IN STD_LOGIC;
        out_encrypted : OUT STD_LOGIC_VECTOR(7 DOWNTO 0);
        out_deciphered : OUT STD_LOGIC_VECTOR(7 DOWNTO 0)
    );
END enc_dec_top;

ARCHITECTURE enc_dec_top_arch OF enc_dec_top IS
    --encoder to decoder
    SIGNAL enc_to_dec : STD_LOGIC_VECTOR(7 DOWNTO 0);

    --
BEGIN
    out_encrypted <= enc_to_dec;
    u_encoder : ENTITY work.codec_top(codec_top_arch)
        PORT MAP(
            tmessage => in_message,
            treset_n => reset,
            tclk => clock,
            encrypted => enc_to_dec
        );

    u_decoder : ENTITY work.codec_top(codec_top_arch)
        PORT MAP(
            tmessage => enc_to_dec,
            treset_n => reset,
            tclk => clock,
            encrypted => out_deciphered
        );
END enc_dec_top_arch;

testbench.vhd
LIBRARY ieee;
USE ieee.std_logic_1164.ALL;

ENTITY testbench IS
END testbench;

ARCHITECTURE test OF testbench IS
    SIGNAL clk : STD_LOGIC := '0';
    SIGNAL reset_n : STD_LOGIC := '0';
    SIGNAL cipher_out : STD_LOGIC_VECTOR(15 DOWNTO 0);
    SIGNAL message : STD_LOGIC_VECTOR(7 DOWNTO 0);
    SIGNAL encrypted_text : STD_LOGIC_VECTOR(7 DOWNTO 0);
    SIGNAL deciphered_text : STD_LOGIC_VECTOR(7 DOWNTO 0);

BEGIN
    -- Instantiate LFSR
    codec_inst : ENTITY work.enc_dec_top
        PORT MAP(
            in_message => message,
            reset => reset_n,
            clock => clk,
            out_encrypted => encrypted_text,
            out_deciphered => deciphered_text
        );

    -- Clock generation
    clk <= NOT clk AFTER 5 ns;

    -- Test stimulus
    PROCESS
    BEGIN
        -- Hold in reset for initial cycles
        -- Expected: cipher_out held at x"A5A5" (init value); cipher_text = x"A5" XOR x"00" = x"A5"
        reset_n <= '0';
        message <= x"00";
        WAIT FOR 20 ns;

        -- Release reset
        -- Expected: LFSR begins shifting and produces new keystream each clock; cipher_text evolves
        reset_n <= '1';
        message <= x"AA";
        WAIT FOR 20 ns;

        -- Change message
        -- Expected: LFSR continues shifting; cipher_text = cipher_out(7:0) XOR x"55"
        message <= x"55";
        WAIT FOR 20 ns;

        -- Change message again
        -- Expected: LFSR continues shifting; cipher_text = cipher_out(7:0) XOR x"FF"
        message <= x"FF";
        WAIT FOR 20 ns;

        -- Change message
        -- Expected: LFSR continues shifting; cipher_text = cipher_out(7:0) XOR x"AA"
        message <= x"AA";
        WAIT FOR 20 ns;

        -- End test stimulus and idle
        WAIT;
    END PROCESS;

END test;

hardware/output.vcd
$date
  Wed Apr 08 23:38:05 2026
$end
$version
  GHDL v0
$end
$timescale
  1 fs
$end
$scope module standard $end
$upscope $end
$scope module std_logic_1164 $end
$upscope $end
$scope module numeric_std $end
$upscope $end
$scope module testbench $end
$var reg 1 ! clk $end
$var reg 1 " reset_n $end
$var reg 16 # cipher_out[15:0] $end
$var reg 8 $ message[7:0] $end
$var reg 8 % encrypted_text[7:0] $end
$var reg 8 & deciphered_text[7:0] $end
$scope module codec_inst $end
$var reg 8 ' in_message[7:0] $end
$var reg 1 ( reset $end
$var reg 1 ) clock $end
$var reg 8 * out_encrypted[7:0] $end
$var reg 8 + out_deciphered[7:0] $end
$var reg 8 , enc_to_dec[7:0] $end
$scope module u_encoder $end
$var reg 8 - tmessage[7:0] $end
$var reg 1 . treset_n $end
$var reg 1 / tclk $end
$var reg 8 0 encrypted[7:0] $end
$var reg 16 1 cipher_wire[15:0] $end
$var reg 8 2 encrypted_message_wire[7:0] $end
$scope module u_lfsr $end
$var reg 1 3 reset_n $end
$var reg 1 4 clk $end
$var reg 16 5 cipher_out[15:0] $end
$var reg 1 6 temp $end
$var reg 16 7 to_out[15:0] $end
$upscope $end
$scope module u_codec $end
$var reg 16 8 cipher[15:0] $end
$var reg 8 9 message[7:0] $end
$var reg 8 : out_text[7:0] $end
$upscope $end
$upscope $end
$scope module u_decoder $end
$var reg 8 ; tmessage[7:0] $end
$var reg 1 < treset_n $end
$var reg 1 = tclk $end
$var reg 8 > encrypted[7:0] $end
$var reg 16 ? cipher_wire[15:0] $end
$var reg 8 @ encrypted_message_wire[7:0] $end
$scope module u_lfsr $end
$var reg 1 A reset_n $end
$var reg 1 B clk $end
$var reg 16 C cipher_out[15:0] $end
$var reg 1 D temp $end
$var reg 16 E to_out[15:0] $end
$upscope $end
$scope module u_codec $end
$var reg 16 F cipher[15:0] $end
$var reg 8 G message[7:0] $end
$var reg 8 H out_text[7:0] $end
$upscope $end
$upscope $end
$upscope $end
$upscope $end
$enddefinitions $end
#0
0!
0"
bUUUUUUUUUUUUUUUU #
b00000000 $
b10100101 %
b00000000 &
b00000000 '
0(
0)
b10100101 *
b00000000 +
b10100101 ,
b00000000 -
0.
0/
b10100101 0
b1010010110100101 1
b10100101 2
03
04
b1010010110100101 5
06
b1010010110100101 7
b1010010110100101 8
b00000000 9
b10100101 :
b10100101 ;
0<
0=
b00000000 >
b1010010110100101 ?
b00000000 @
0A
0B
b1010010110100101 C
0D
b1010010110100101 E
b1010010110100101 F
b10100101 G
b00000000 H
#5000000
1!
1)
1/
14
1=
1B
#10000000
0!
0)
0/
04
0=
0B
#15000000
1!
1)
1/
14
1=
1B
#20000000
0!
1"
b10101010 $
b00001111 %
b10101010 &
b10101010 '
1(
0)
b00001111 *
b10101010 +
b00001111 ,
b10101010 -
1.
0/
b00001111 0
b00001111 2
13
04
b10101010 9
b00001111 :
b00001111 ;
1<
0=
b10101010 >
b10101010 @
1A
0B
b00001111 G
b10101010 H
#25000000
1!
b01111000 %
b10101010 &
1)
b01111000 *
b10101010 +
b01111000 ,
1/
b01111000 0
b0101001011010010 1
b01111000 2
14
b0101001011010010 5
b0101001011010010 7
b0101001011010010 8
b01111000 :
b01111000 ;
1=
b10101010 >
b0101001011010010 ?
b10101010 @
1B
b0101001011010010 C
b0101001011010010 E
b0101001011010010 F
b01111000 G
b10101010 H
#30000000
0!
0)
0/
04
0=
0B
#35000000
1!
b11000011 %
b10101010 &
1)
b11000011 *
b10101010 +
b11000011 ,
1/
b11000011 0
b0010100101101001 1
b11000011 2
14
b0010100101101001 5
b0010100101101001 7
b0010100101101001 8
b11000011 :
b11000011 ;
1=
b10101010 >
b0010100101101001 ?
b10101010 @
1B
b0010100101101001 C
b0010100101101001 E
b0010100101101001 F
b11000011 G
b10101010 H
#40000000
0!
b01010101 $
b00111100 %
b01010101 &
b01010101 '
0)
b00111100 *
b01010101 +
b00111100 ,
b01010101 -
0/
b00111100 0
b00111100 2
04
b01010101 9
b00111100 :
b00111100 ;
0=
b01010101 >
b01010101 @
0B
b00111100 G
b01010101 H
#45000000
1!
b11100001 %
b01010101 &
1)
b11100001 *
b01010101 +
b11100001 ,
1/
b11100001 0
b0001010010110100 1
b11100001 2
14
b0001010010110100 5
b0001010010110100 7
b0001010010110100 8
b11100001 :
b11100001 ;
1=
b01010101 >
b0001010010110100 ?
b01010101 @
1B
b0001010010110100 C
b0001010010110100 E
b0001010010110100 F
b11100001 G
b01010101 H
#50000000
0!
0)
0/
04
0=
0B
#55000000
1!
b00001111 %
b01010101 &
1)
b00001111 *
b01010101 +
b00001111 ,
1/
b00001111 0
b0000101001011010 1
b00001111 2
14
b0000101001011010 5
b0000101001011010 7
b0000101001011010 8
b00001111 :
b00001111 ;
1=
b01010101 >
b0000101001011010 ?
b01010101 @
1B
b0000101001011010 C
b0000101001011010 E
b0000101001011010 F
b00001111 G
b01010101 H
#60000000
0!
b11111111 $
b10100101 %
b11111111 &
b11111111 '
0)
b10100101 *
b11111111 +
b10100101 ,
b11111111 -
0/
b10100101 0
b10100101 2
04
b11111111 9
b10100101 :
b10100101 ;
0=
b11111111 >
b11111111 @
0B
b10100101 G
b11111111 H
#65000000
1!
b11010010 %
b11111111 &
1)
b11010010 *
b11111111 +
b11010010 ,
1/
b11010010 0
b0000010100101101 1
b11010010 2
14
b0000010100101101 5
16
b0000010100101101 7
b0000010100101101 8
b11010010 :
b11010010 ;
1=
b11111111 >
b0000010100101101 ?
b11111111 @
1B
b0000010100101101 C
1D
b0000010100101101 E
b0000010100101101 F
b11010010 G
b11111111 H
#70000000
0!
0)
0/
04
0=
0B
#75000000
1!
b01101001 %
b11111111 &
1)
b01101001 *
b11111111 +
b01101001 ,
1/
b01101001 0
b1000001010010110 1
b01101001 2
14
b1000001010010110 5
b1000001010010110 7
b1000001010010110 8
b01101001 :
b01101001 ;
1=
b11111111 >
b1000001010010110 ?
b11111111 @
1B
b1000001010010110 C
b1000001010010110 E
b1000001010010110 F
b01101001 G
b11111111 H
#80000000
0!
b10101010 $
b00111100 %
b10101010 &
b10101010 '
0)
b00111100 *
b10101010 +
b00111100 ,
b10101010 -
0/
b00111100 0
b00111100 2
04
b10101010 9
b00111100 :
b00111100 ;
0=
b10101010 >
b10101010 @
0B
b00111100 G
b10101010 H
#85000000
1!
b11100001 %
b10101010 &
1)
b11100001 *
b10101010 +
b11100001 ,
1/
b11100001 0
b1100000101001011 1
b11100001 2
14
b1100000101001011 5
06
b1100000101001011 7
b1100000101001011 8
b11100001 :
b11100001 ;
1=
b10101010 >
b1100000101001011 ?
b10101010 @
1B
b1100000101001011 C
0D
b1100000101001011 E
b1100000101001011 F
b11100001 G
b10101010 H
#90000000
0!
0)
0/
04
0=
0B
#95000000
1!
b00001111 %
b10101010 &
1)
b00001111 *
b10101010 +
b00001111 ,
1/
b00001111 0
b0110000010100101 1
b00001111 2
14
b0110000010100101 5
16
b0110000010100101 7
b0110000010100101 8
b00001111 :
b00001111 ;
1=
b10101010 >
b0110000010100101 ?
b10101010 @
1B
b0110000010100101 C
1D
b0110000010100101 E
b0110000010100101 F
b00001111 G
b10101010 H
#100000000
0!
0)
0/
04
0=
0B
#105000000
1!
b11111000 %
b10101010 &
1)
b11111000 *
b10101010 +
b11111000 ,
1/
b11111000 0
b1011000001010010 1
b11111000 2
14
b1011000001010010 5
06
b1011000001010010 7
b1011000001010010 8
b11111000 :
b11111000 ;
1=
b10101010 >
b1011000001010010 ?
b10101010 @
1B
b1011000001010010 C
0D
b1011000001010010 E
b1011000001010010 F
b11111000 G
b10101010 H
#110000000
0!
0)
0/
04
0=
0B
#115000000
1!
b10000011 %
b10101010 &
1)
b10000011 *
b10101010 +
b10000011 ,
1/
b10000011 0
b0101100000101001 1
b10000011 2
14
b0101100000101001 5
b0101100000101001 7
b0101100000101001 8
b10000011 :
b10000011 ;
1=
b10101010 >
b0101100000101001 ?
b10101010 @
1B
b0101100000101001 C
b0101100000101001 E
b0101100000101001 F
b10000011 G
b10101010 H
#120000000
0!
0)
0/
04
0=
0B
#125000000
1!
b10111110 %
b10101010 &
1)
b10111110 *
b10101010 +
b10111110 ,
1/
b10111110 0
b0010110000010100 1
b10111110 2
14
b0010110000010100 5
16
b0010110000010100 7
b0010110000010100 8
b10111110 :
b10111110 ;
1=
b10101010 >
b0010110000010100 ?
b10101010 @
1B
b0010110000010100 C
1D
b0010110000010100 E
b0010110000010100 F
b10111110 G
b10101010 H
#130000000
0!
0)
0/
04
0=
0B
#135000000
1!
b10100000 %
b10101010 &
1)
b10100000 *
b10101010 +
b10100000 ,
1/
b10100000 0
b1001011000001010 1
b10100000 2
14
b1001011000001010 5
b1001011000001010 7
b1001011000001010 8
b10100000 :
b10100000 ;
1=
b10101010 >
b1001011000001010 ?
b10101010 @
1B
b1001011000001010 C
b1001011000001010 E
b1001011000001010 F
b10100000 G
b10101010 H
#140000000
0!
0)
0/
04
0=
0B
#145000000
1!
b10101111 %
b10101010 &
1)
b10101111 *
b10101010 +
b10101111 ,
1/
b10101111 0
b1100101100000101 1
b10101111 2
14
b1100101100000101 5
06
b1100101100000101 7
b1100101100000101 8
b10101111 :
b10101111 ;
1=
b10101010 >
b1100101100000101 ?
b10101010 @
1B
b1100101100000101 C
0D
b1100101100000101 E
b1100101100000101 F
b10101111 G
b10101010 H
#150000000
0!
0)
0/
04
0=
0B
#155000000
1!
b00101000 %
b10101010 &
1)
b00101000 *
b10101010 +
b00101000 ,
1/
b00101000 0
b0110010110000010 1
b00101000 2
14
b0110010110000010 5
b0110010110000010 7
b0110010110000010 8
b00101000 :
b00101000 ;
1=
b10101010 >
b0110010110000010 ?
b10101010 @
1B
b0110010110000010 C
b0110010110000010 E
b0110010110000010 F
b00101000 G
b10101010 H
#160000000
0!
0)
0/
04
0=
0B
#165000000
1!
b01101011 %
b10101010 &
1)
b01101011 *
b10101010 +
b01101011 ,
1/
b01101011 0
b0011001011000001 1
b01101011 2
14
b0011001011000001 5
16
b0011001011000001 7
b0011001011000001 8
b01101011 :
b01101011 ;
1=
b10101010 >
b0011001011000001 ?
b10101010 @
1B
b0011001011000001 C
1D
b0011001011000001 E
b0011001011000001 F
b01101011 G
b10101010 H
#170000000
0!
0)
0/
04
0=
0B
#175000000
1!
b11001010 %
b10101010 &
1)
b11001010 *
b10101010 +
b11001010 ,
1/
b11001010 0
b1001100101100000 1
b11001010 2
14
b1001100101100000 5
06
b1001100101100000 7
b1001100101100000 8
b11001010 :
b11001010 ;
1=
b10101010 >
b1001100101100000 ?
b10101010 @
1B
b1001100101100000 C
0D
b1001100101100000 E
b1001100101100000 F
b11001010 G
b10101010 H
#180000000
0!
0)
0/
04
0=
0B
#185000000
1!
b00011010 %
b10101010 &
1)
b00011010 *
b10101010 +
b00011010 ,
1/
b00011010 0
b0100110010110000 1
b00011010 2
14
b0100110010110000 5
b0100110010110000 7
b0100110010110000 8
b00011010 :
b00011010 ;
1=
b10101010 >
b0100110010110000 ?
b10101010 @
1B
b0100110010110000 C
b0100110010110000 E
b0100110010110000 F
b00011010 G
b10101010 H
#190000000
0!
0)
0/
04
0=
0B
#195000000
1!
b11110010 %
b10101010 &
1)
b11110010 *
b10101010 +
b11110010 ,
1/
b11110010 0
b0010011001011000 1
b11110010 2
14
b0010011001011000 5
16
b0010011001011000 7
b0010011001011000 8
b11110010 :
b11110010 ;
1=
b10101010 >
b0010011001011000 ?
b10101010 @
1B
b0010011001011000 C
1D
b0010011001011000 E
b0010011001011000 F
b11110010 G
b10101010 H
